kappamodules/__init__.py
kappamodules/architectures/__init__.py
kappamodules/architectures/upt/__init__.py
kappamodules/architectures/upt/perceiver_decoder.py
kappamodules/attention/__init__.py
kappamodules/attention/dot_product_attention.py
kappamodules/attention/dot_product_attention_slow.py
kappamodules/attention/efficient_attention.py
kappamodules/attention/linformer_attention.py
kappamodules/attention/mmdit_dot_product_attention.py
kappamodules/attention/mmmdit_dot_product_attention.py
kappamodules/attention/perceiver_attention.py
kappamodules/attention/transsolver_attention.py
kappamodules/convolution/__init__.py
kappamodules/convolution/convnext.py
kappamodules/diffaug/__init__.py
kappamodules/diffaug/gaussian_blur.py
kappamodules/functional/__init__.py
kappamodules/functional/attention.py
kappamodules/functional/logscale.py
kappamodules/functional/patchify.py
kappamodules/functional/pos_embed.py
kappamodules/init/__init__.py
kappamodules/init/functional.py
kappamodules/layers/__init__.py
kappamodules/layers/async_batchnorm.py
kappamodules/layers/continuous_pos_embed.py
kappamodules/layers/continuous_sincos_embed.py
kappamodules/layers/datanorm.py
kappamodules/layers/drop_path.py
kappamodules/layers/identity.py
kappamodules/layers/ignore_args_and_kwargs_wrapper.py
kappamodules/layers/layer_scale.py
kappamodules/layers/layernorm.py
kappamodules/layers/learned_batchnorm.py
kappamodules/layers/linear_projection.py
kappamodules/layers/normalize.py
kappamodules/layers/paramless_batchnorm.py
kappamodules/layers/regular_grid_sincos_embed.py
kappamodules/layers/residual.py
kappamodules/layers/rms_norm.py
kappamodules/layers/sequential.py
kappamodules/layers/weight_norm_linear.py
kappamodules/losses/__init__.py
kappamodules/losses/l1_loss.py
kappamodules/losses/mse_loss.py
kappamodules/mlp/__init__.py
kappamodules/mlp/mlp.py
kappamodules/mlp/prenorm_mlp_block.py
kappamodules/mlp/swiglu_mlp.py
kappamodules/modulation/__init__.py
kappamodules/modulation/dit.py
kappamodules-0.1.112.dist-info/LICENSE
kappamodules-0.1.112.dist-info/METADATA
kappamodules-0.1.112.dist-info/WHEEL
kappamodules-0.1.112.dist-info/top_level.txt
kappamodules-0.1.112.dist-info/RECORD
