Metadata-Version: 2.1
Name: kappamodules
Version: 0.1.112
Summary: efficient building blocks for pytorch models
Home-page: https://github.com/BenediktAlkin/KappaModules
Project-URL: Source Code, https://github.com/BenediktAlkin/KappaModules
Project-URL: Bug Tracker, https://github.com/BenediktAlkin/KappaModules/issues
Classifier: Programming Language :: Python :: 3
Classifier: License :: OSI Approved :: MIT License
Classifier: Operating System :: OS Independent
Requires-Python: >=3.6
License-File: LICENSE
Requires-Dist: torch
Requires-Dist: einops
Requires-Dist: numpy
